setup.py
django_next_previous.egg-info/PKG-INFO
django_next_previous.egg-info/SOURCES.txt
django_next_previous.egg-info/dependency_links.txt
django_next_previous.egg-info/top_level.txt
next_previous/__init__.py