Metadata-Version: 1.0
Name: django-next-previous
Version: 0.1
Summary: Django model mixin for easy retrieval of the 'next' and 'previous' objects.
Home-page: http://code.playfire.com/
Author: Playfire.com
Author-email: tech@playfire.com
License: BSD
Platform: UNKNOWN
